LICENSE.txt
MANIFEST.in
README.rst
pyorcy.py
setup.cfg
setup.py
fastthreadpool/__init__.py
fastthreadpool/fastthreadpool.py
fastthreadpool.egg-info/PKG-INFO
fastthreadpool.egg-info/SOURCES.txt
fastthreadpool.egg-info/dependency_links.txt
fastthreadpool.egg-info/requires.txt
fastthreadpool.egg-info/top_level.txt