Metadata-Version: 2.1
Name: fastthreadpool
Version: 1.4.1
Summary: An efficient and leightweight thread pool.
Home-page: https://github.com/brmmm3/fastthreadpool
Author: Martin Bammer
Author-email: mrbm74@gmail.com
License: MIT
Download-URL: https://github.com/brmmm3/fastthreadpool/releases/download/1.4.1/fastthreadpool-1.4.1.tar.gz
Keywords: fast threading thread pool
Platform: UNKNOWN
Classifier: Development Status :: 5 - Production/Stable
Classifier: Intended Audience :: Developers
Classifier: Topic :: Software Development :: Build Tools
Classifier: License :: OSI Approved :: MIT License
Classifier: Operating System :: OS Independent
Classifier: Programming Language :: Python :: 2
Classifier: Programming Language :: Python :: 2.7
Classifier: Programming Language :: Python :: 3
Classifier: Programming Language :: Python :: 3.4
Classifier: Programming Language :: Python :: 3.5
Classifier: Programming Language :: Python :: 3.6
